Workbook
Name SegmentaciónDeDatos_Categoría: #N/A
Name SegmentaciónDeDatos_Mes: #N/A
Name SegmentaciónDeDatos_Región: #N/A

Sheet DashboardFinal
B1: Motor de Análisis de Ventas
C2: Análisis por Vendedor, Región y Categoría | 2026
B3: VENTAS TOTALES | F3: MARGEN % | I3: UNIDADES VENDIDAS | AD3: concepto | AE3: importe
C4: ='Soporte Dashboard'!J2 -> 199726100 | G4: ='Soporte Dashboard'!N2 -> 0.32434581 | J4: ='Soporte Dashboard'!L2 -> 12027 | AD4: Ventas | AE4: =GETPIVOTDATA("Suma de Venta Total",'Soporte Dashboard'!$J$1) -> 199726100
AD5: Costos | AE5: =-GETPIVOTDATA("Suma de Costo Total",'Soporte Dashboard'!$J$1) -> -134945776
AD6: Margen | AE6: =GETPIVOTDATA("Suma de Margen $",'Soporte Dashboard'!$J$1) -> 64780324
AB10: ="El costo absorbe el "&TEXT(1-G4,"0,00%")&" de las ventas y deja un margen del "&TEXT(G4,"0,00%") -> El costo absorbe el 67,57% de las ventas y deja un margen del 32,43%

Sheet Soporte Dashboard
A1: Región | B1: Ventas por Región | D1: Categoria | E1: Ventas por Categoría | G1: Vendedor | H1: Ventas por Vendedor | J1: Suma de Venta Total | K1: Suma de Margen $ | L1: Suma de Unidades | M1: Suma de Costo Total | N1: Margen %
A2: AMBA | B2: 66218400 | D2: Camas | E2: 50611300 | G2: Agustín | H2: 30734800 | J2: 199726100 | K2: 64780324 | L2: 12027 | M2: 134945776 | N2: ='Soporte Dashboard'!K2/'Soporte Dashboard'!J2 -> 0.32434581
A3: Centro | B3: 39832400 | D3: Comederos | E3: 23012400 | G3: Carolina | H3: 29960200
A4: Cuyo | B4: 26116400 | D4: Higiene | E4: 17366800 | G4: Demian | H4: 29443000
A5: Norte | B5: 36411200 | D5: Juguetes | E5: 11187200 | G5: Germán | H5: 33903200
A6: Sur | B6: 31147700 | D6: Transporte | E6: 97548400 | G6: Hernán | H6: 36742700
A7: Total general | B7: 199726100 | D7: Total general | E7: 199726100 | G7: Lucía | H7: 38942200
G8: Total general | H8: 199726100

Sheet Datos
A1: ID Venta | B1: Fecha | C1: Mes | D1: Vendedor | E1: Región | F1: Categoría | G1: Producto | H1: Canal | I1: Unidades | J1: Precio Unitario | K1: Venta Total | L1: Costo Unitario | M1: Costo Total | N1: Margen $ | O1: Margen %
A2: V-0001 | B2: 46063 | C2: Febrero | D2: Agustín | E2: AMBA | F2: Comederos | G2: Comedero Doble | H2: Retail | I2: 34 | J2: 6600 | K2: =Tbl_Datos[[#This Row],[Unidades]]*Tbl_Datos[[#This Row],[Precio Unitario]] -> 224400 | L2: {=_xlfn.IFS(F2="Camas",J2*68%,F2="Comederos",J2*60%,F2="Higiene",J2*55%,F2="Juguetes",J2*62%,F2="Transporte",J2*72%)} -> 3960 | M2: =I2*L2 -> 134640 | N2: =K2-M2 -> 89760 | O2: =N2/K2 -> 0.4
A3: V-0002 | B3: 46263 | C3: Agosto | D3: Lucía | E3: Centro | F3: Camas | G3: Cama Rectangular M | H3: Retail | I3: 10 | J3: 20800 | K3: =Tbl_Datos[[#This Row],[Unidades]]*Tbl_Datos[[#This Row],[Precio Unitario]] -> 208000 | L3: {=_xlfn.IFS(F3="Camas",J3*68%,F3="Comederos",J3*60%,F3="Higiene",J3*55%,F3="Juguetes",J3*62%,F3="Transporte",J3*72%)} -> 14144 | M3: =I3*L3 -> 141440 | N3: =K3-M3 -> 66560 | O3: =N3/K3 -> 0.32
A4: V-0003 | B4: 46165 | C4: Mayo | D4: Hernán | E4: Norte | F4: Juguetes | G4: Pelota Goma | H4: Distribuidor | I4: 53 | J4: 3100 | K4: =Tbl_Datos[[#This Row],[Unidades]]*Tbl_Datos[[#This Row],[Precio Unitario]] -> 164300 | L4: {=_xlfn.IFS(F4="Camas",J4*68%,F4="Comederos",J4*60%,F4="Higiene",J4*55%,F4="Juguetes",J4*62%,F4="Transporte",J4*72%)} -> 1922 | M4: =I4*L4 -> 101866 | N4: =K4-M4 -> 62434 | O4: =N4/K4 -> 0.38
A5: V-0004 | B5: 46067 | C5: Febrero | D5: Demian | E5: AMBA | F5: Transporte | G5: Transportadora L | H5: Mayorista | I5: 52 | J5: 48300 | K5: =Tbl_Datos[[#This Row],[Unidades]]*Tbl_Datos[[#This Row],[Precio Unitario]] -> 2511600 | L5: {=_xlfn.IFS(F5="Camas",J5*68%,F5="Comederos",J5*60%,F5="Higiene",J5*55%,F5="Juguetes",J5*62%,F5="Transporte",J5*72%)} -> 34776 | M5: =I5*L5 -> 1808352 | N5: =K5-M5 -> 703248 | O5: =N5/K5 -> 0.28
A6: V-0005 | B6: 46082 | C6: Marzo | D6: Carolina | E6: AMBA | F6: Camas | G6: Cama Rectangular S | H6: Distribuidor | I6: 54 | J6: 15600 | K6: =Tbl_Datos[[#This Row],[Unidades]]*Tbl_Datos[[#This Row],[Precio Unitario]] -> 842400 | L6: {=_xlfn.IFS(F6="Camas",J6*68%,F6="Comederos",J6*60%,F6="Higiene",J6*55%,F6="Juguetes",J6*62%,F6="Transporte",J6*72%)} -> 10608 | M6: =I6*L6 -> 572832 | N6: =K6-M6 -> 269568 | O6: =N6/K6 -> 0.32
A7: V-0006 | B7: 46079 | C7: Febrero | D7: Agustín | E7: AMBA | F7: Camas | G7: Cama Rectangular L | H7: Retail | I7: 20 | J7: 27700 | K7: =Tbl_Datos[[#This Row],[Unidades]]*Tbl_Datos[[#This Row],[Precio Unitario]] -> 554000 | L7: {=_xlfn.IFS(F7="Camas",J7*68%,F7="Comederos",J7*60%,F7="Higiene",J7*55%,F7="Juguetes",J7*62%,F7="Transporte",J7*72%)} -> 18836 | M7: =I7*L7 -> 376720 | N7: =K7-M7 -> 177280 | O7: =N7/K7 -> 0.32
A8: V-0007 | B8: 46032 | C8: Enero | D8: Germán | E8: Centro | F8: Comederos | G8: Comedero Simple | H8: Distribuidor | I8: 35 | J8: 3900 | K8: =Tbl_Datos[[#This Row],[Unidades]]*Tbl_Datos[[#This Row],[Precio Unitario]] -> 136500 | L8: {=_xlfn.IFS(F8="Camas",J8*68%,F8="Comederos",J8*60%,F8="Higiene",J8*55%,F8="Juguetes",J8*62%,F8="Transporte",J8*72%)} -> 2340 | M8: =I8*L8 -> 81900 | N8: =K8-M8 -> 54600 | O8: =N8/K8 -> 0.4
A9: V-0008 | B9: 46025 | C9: Enero | D9: Demian | E9: Cuyo | F9: Transporte | G9: Transportadora L | H9: Mayorista | I9: 19 | J9: 50700 | K9: =Tbl_Datos[[#This Row],[Unidades]]*Tbl_Datos[[#This Row],[Precio Unitario]] -> 963300 | L9: {=_xlfn.IFS(F9="Camas",J9*68%,F9="Comederos",J9*60%,F9="Higiene",J9*55%,F9="Juguetes",J9*62%,F9="Transporte",J9*72%)} -> 36504 | M9: =I9*L9 -> 693576 | N9: =K9-M9 -> 269724 | O9: =N9/K9 -> 0.28
A10: V-0009 | B10: 46156 | C10: Mayo | D10: Hernán | E10: Centro | F10: Comederos | G10: Comedero Antideslizante | H10: Distribuidor | I10: 51 | J10: 8100 | K10: =Tbl_Datos[[#This Row],[Unidades]]*Tbl_Datos[[#This Row],[Precio Unitario]] -> 413100 | L10: {=_xlfn.IFS(F10="Camas",J10*68%,F10="Comederos",J10*60%,F10="Higiene",J10*55%,F10="Juguetes",J10*62%,F10="Transporte",J10*72%)} -> 4860 | M10: =I10*L10 -> 247860 | N10: =K10-M10 -> 165240 | O10: =N10/K10 -> 0.4
A11: V-0010 | B11: 46159 | C11: Mayo | D11: Demian | E11: Cuyo | F11: Transporte | G11: Transportadora S | H11: Retail | I11: 33 | J11: 30400 | K11: =Tbl_Datos[[#This Row],[Unidades]]*Tbl_Datos[[#This Row],[Precio Unitario]] -> 1003200 | L11: {=_xlfn.IFS(F11="Camas",J11*68%,F11="Comederos",J11*60%,F11="Higiene",J11*55%,F11="Juguetes",J11*62%,F11="Transporte",J11*72%)} -> 21888 | M11: =I11*L11 -> 722304 | N11: =K11-M11 -> 280896 | O11: =N11/K11 -> 0.28
A12: V-0011 | B12: 46031 | C12: Enero | D12: Germán | E12: Centro | F12: Higiene | G12: Bandeja Sanitaria | H12: Mayorista | I12: 45 | J12: 14000 | K12: =Tbl_Datos[[#This Row],[Unidades]]*Tbl_Datos[[#This Row],[Precio Unitario]] -> 630000 | L12: {=_xlfn.IFS(F12="Camas",J12*68%,F12="Comederos",J12*60%,F12="Higiene",J12*55%,F12="Juguetes",J12*62%,F12="Transporte",J12*72%)} -> 7700 | M12: =I12*L12 -> 346500 | N12: =K12-M12 -> 283500 | O12: =N12/K12 -> 0.45
A13: V-0012 | B13: 46175 | C13: Junio | D13: Lucía | E13: Centro | F13: Camas | G13: Cama Rectangular L | H13: Distribuidor | I13: 37 | J13: 27200 | K13: =Tbl_Datos[[#This Row],[Unidades]]*Tbl_Datos[[#This Row],[Precio Unitario]] -> 1006400 | L13: {=_xlfn.IFS(F13="Camas",J13*68%,F13="Comederos",J13*60%,F13="Higiene",J13*55%,F13="Juguetes",J13*62%,F13="Transporte",J13*72%)} -> 18496 | M13: =I13*L13 -> 684352 | N13: =K13-M13 -> 322048 | O13: =N13/K13 -> 0.32
... A361: V-0360 | B361: 46187 | C361: Junio | D361: Germán | E361: AMBA | F361: Juguetes | G361: Juguete Interactivo | H361: Distribuidor | I361: 31 | J361: 10600 | K361: =Tbl_Datos[[#This Row],[Unidades]]*Tbl_Datos[[#This Row],[Precio Unitario]] -> 328600 | L361: {=_xlfn.IFS(F361="Camas",J361*68%,F361="Comederos",J361*60%,F361="Higiene",J361*55%,F361="Juguetes",J361*62%,F361="Transporte",J361*72%)} -> 6572 | M361: =I361*L361 -> 203732 | N361: =K361-M361 -> 124868 | O361: =N361/K361 -> 0.38
